README.md
setup.cfg
setup.py
fastalchemy/__init__.py
fastalchemy.egg-info/PKG-INFO
fastalchemy.egg-info/SOURCES.txt
fastalchemy.egg-info/dependency_links.txt
fastalchemy.egg-info/requires.txt
fastalchemy.egg-info/top_level.txt