Metadata-Version: 2.1
Name: fastalchemy
Version: 0.1.1
Summary: A SQLAlchemy middleware for FastAPI
Home-page: https://github.com/cloudeyes/fastalchemy
Author: Joseph Kim
Author-email: cloudeyes@gmail.com
License: MIT
Download-URL: https://github.com/cloudeyes/fastalchemy/archive/v0.1.1.tar.gz
Keywords: fastapi,middleware,sqlalchemy,plugin
Platform: UNKNOWN
Classifier: Development Status :: 3 - Alpha
Classifier: Intended Audience :: Developers
Classifier: Topic :: Software Development :: Build Tools
Classifier: License :: OSI Approved :: MIT License
Classifier: Programming Language :: Python :: 3
Classifier: Programming Language :: Python :: 3.7
Classifier: Programming Language :: Python :: 3.8
